LICENSE.txt
MANIFEST.in
README.rst
setup.cfg
setup.py
ClassificaIO/.DS_Store
ClassificaIO/ClassificaIO.py
ClassificaIO/__init__.py
ClassificaIO/logo_Lab_round.png
ClassificaIO.egg-info/PKG-INFO
ClassificaIO.egg-info/SOURCES.txt
ClassificaIO.egg-info/dependency_links.txt
ClassificaIO.egg-info/not-zip-safe
ClassificaIO.egg-info/requires.txt
ClassificaIO.egg-info/top_level.txt