Metadata-Version: 1.1
Name: ClassificaIO
Version: 1.1.5.1
Summary: Graphical User Interface for machine learning classification algorithms from scikit-learn
Home-page: https://github.com/gmiaslab/ClassificaIO
Author: G. Mias Lab
Author-email: gmiaslab@gmail.com
License: MIT
Download-URL: https://github.com/gmiaslab/ClassificaIO/archive/1.1.5.1.tar.gz
Keywords: machine learning,classification,bioinformatics
Platform: UNKNOWN
Classifier: License :: OSI Approved :: MIT License
Classifier: Programming Language :: Python :: 3
Classifier: Topic :: Scientific/Engineering :: Bio-Informatics
Classifier: Intended Audience :: Science/Research
Classifier: Intended Audience :: Education
Classifier: Intended Audience :: Developers
Classifier: Intended Audience :: End Users/Desktop
Classifier: Operating System :: MacOS
Classifier: Operating System :: Microsoft :: Windows
Classifier: Operating System :: Unix
Classifier: Topic :: Education
Classifier: Topic :: Utilities
